{
    "suggest.triggerAfterInsertEnter": true,
    "suggest.noselect": false,
    "suggest.minTriggerInputLength": 2,
    "suggest.acceptSuggestionOnCommitCharacter": true,
    "suggest.snippetIndicator": " ►",
    "suggest.enablePreview": true,
    "coc.preferences.hoverTarget": "float",
    "coc.preferences.formatOnType": true,
    "coc.preferences.formatOnSaveFiletypes": [
      "go"
    ],
    "solargraph.formatting": true,
    "solargraph.autoformat": true,
    "solargraph.diagnostics": true,
    "tsserver.formatOnType": true,
    "languageserver": {
      "clangd": {
        "command": "clangd",
        "rootPatterns": ["compile_flags.txt", "compile_commands.json"],
        "filetypes": ["c", "cpp", "objc", "objcpp"]
      }
    }
}
